aiida_yambo/__init__.py
aiida_yambo/calculations/__init__.py
aiida_yambo/calculations/yambo.py
aiida_yambo/commands/__init__.py
aiida_yambo/commands/options.py
aiida_yambo/commands/plotting.py
aiida_yambo/commands/utils.py
aiida_yambo/commands/validators.py
aiida_yambo/parsers/__init__.py
aiida_yambo/parsers/parsers.py
aiida_yambo/parsers/utils.py
aiida_yambo/parsers/ext_dep/__init__.py
aiida_yambo/parsers/ext_dep/yambofile.py
aiida_yambo/parsers/ext_dep/yambofolder.py
aiida_yambo/utils/__init__.py
aiida_yambo/utils/common_helpers.py
aiida_yambo/utils/parallel_namelists.py
aiida_yambo/utils/parallelism_finder.py
aiida_yambo/workflows/__init__.py
aiida_yambo/workflows/fix.py
aiida_yambo/workflows/yamboconvergence.py
aiida_yambo/workflows/yamborestart.py
aiida_yambo/workflows/yambowf.py
aiida_yambo/workflows/qe_wfls/__init__.py
aiida_yambo/workflows/qe_wfls/qe_structure.py
aiida_yambo/workflows/qe_wfls/qeconv.py
aiida_yambo/workflows/utils/__init__.py
aiida_yambo/workflows/utils/collectors.py
aiida_yambo/workflows/utils/fittings.py
aiida_yambo/workflows/utils/helpers_aiida_qe.py
aiida_yambo/workflows/utils/helpers_aiida_yambo.py
aiida_yambo/workflows/utils/helpers_workflow.py
aiida_yambo/workflows/utils/helpers_yamborestart.py
aiida_yambo/workflows/utils/plotting.py
docs/__init__.py
docs/rtd_settings.py
aiida_yambo-1.3.0.dist-info/LICENSE.txt
aiida_yambo-1.3.0.dist-info/METADATA
aiida_yambo-1.3.0.dist-info/WHEEL
aiida_yambo-1.3.0.dist-info/entry_points.txt
aiida_yambo-1.3.0.dist-info/top_level.txt
aiida_yambo-1.3.0.dist-info/zip-safe
aiida_yambo-1.3.0.dist-info/RECORD
